pddlsim/__init__.py
pddlsim/_asp.py
pddlsim/_serde.py
pddlsim/ast.py
pddlsim/grammar.lark
pddlsim/local.py
pddlsim/parser.py
pddlsim/py.typed
pddlsim/simulation.py
pddlsim/state.py
pddlsim/_cli/__init__.py
pddlsim/_cli/client.py
pddlsim/_cli/server.py
pddlsim/agents/__init__.py
pddlsim/agents/multiple_goal_planner.py
pddlsim/agents/planner.py
pddlsim/agents/previous_state_avoider.py
pddlsim/agents/random_limited_walker.py
pddlsim/agents/random_walker.py
pddlsim/remote/__init__.py
pddlsim/remote/_message.py
pddlsim/remote/client.py
pddlsim/remote/server.py
pddlsim-0.2.0.dev3.dist-info/METADATA
pddlsim-0.2.0.dev3.dist-info/WHEEL
pddlsim-0.2.0.dev3.dist-info/entry_points.txt
pddlsim-0.2.0.dev3.dist-info/licenses/LICENSE
pddlsim-0.2.0.dev3.dist-info/licenses/NOTICE
pddlsim-0.2.0.dev3.dist-info/RECORD
