Metadata-Version: 2.4
Name: pddlsim
Version: 0.2.0.dev3
Summary: PDDL-based simulator for the BIU course "Introduction to Intelligent, Knowledge-Based and Cognitive Systems"
Project-URL: Repository, https://github.com/galk-research/pddlsim
Project-URL: Issues, https://github.com/galk-research/pddlsim/issues
Project-URL: Documentation, https://github.com/galk-research/pddlsim/wiki
Author-email: "Gal A. Kaminka" <galk@cs.biu.ac.il>, Yoav Grimland <miestrode@proton.me>, "Micha S. Molko" <michamolko@gmail.com>
License-Expression: Apache-2.0
License-File: LICENSE
License-File: NOTICE
Keywords: PDDL,agent,simulator
Classifier: Development Status :: 3 - Alpha
Classifier: Intended Audience :: Science/Research
Classifier: Programming Language :: Python :: 3 :: Only
Classifier: Topic :: Scientific/Engineering :: Artificial Intelligence
Requires-Python: >=3.12
Requires-Dist: cbor2>=5.6.5
Requires-Dist: clingo>=5.8.0
Requires-Dist: koda-validate>=5.0.0
Requires-Dist: lark>=1.2.2
Provides-Extra: agents
Requires-Dist: unified-planning[fast-downward]>=1.2.0; extra == 'agents'
Provides-Extra: cli
Requires-Dist: click>=8.2.1; extra == 'cli'
Requires-Dist: unified-planning[fast-downward]>=1.2.0; extra == 'cli'
